devrevthirtyone/Argument.py
devrevthirtyone/EfficientPipeline.py
devrevthirtyone/Manager.py
devrevthirtyone/ReturnType.py
devrevthirtyone/Tool.py
devrevthirtyone/__init__.py
devrevthirtyone/base_model.py
devrevthirtyone/config.py
devrevthirtyone/imports.py
devrevthirtyone/model.py
devrevthirtyone/pipeline.py
devrevthirtyone/pipeline_config.py
devrevthirtyone/retriever.py
devrevthirtyone/utils.py
devrevthirtyone-4.0.1.dist-info/METADATA
devrevthirtyone-4.0.1.dist-info/WHEEL
devrevthirtyone-4.0.1.dist-info/top_level.txt
devrevthirtyone-4.0.1.dist-info/RECORD
